log3/__init__.py
log3/log.py
log3/my_formatter.py
log3/my_logger.py
log3-0.1.7.dist-info/LICENSE.txt
log3-0.1.7.dist-info/METADATA
log3-0.1.7.dist-info/WHEEL
log3-0.1.7.dist-info/top_level.txt
log3-0.1.7.dist-info/RECORD
