Metadata-Version: 2.1
Name: log3
Version: 0.1.7
Summary: High level logging client builtin support for colored terminal output
Home-page: https://github.com/orlandodiaz/log3
Author: Orlando Diaz
Author-email: orlandodiaz.dev@gmail.com
License: UNKNOWN
Platform: UNKNOWN
Classifier: Programming Language :: Python :: 3
Classifier: License :: OSI Approved :: MIT License
Classifier: Operating System :: OS Independent
Requires-Dist: colorama
